smartapi_mcp/__init__.py
smartapi_mcp/__main__.py
smartapi_mcp/awslabs_server.py
smartapi_mcp/cli.py
smartapi_mcp/config.py
smartapi_mcp/py.typed
smartapi_mcp/server.py
smartapi_mcp/smartapi.py
smartapi_mcp-0.1.1.dist-info/licenses/LICENSE
smartapi_mcp-0.1.1.dist-info/METADATA
smartapi_mcp-0.1.1.dist-info/WHEEL
smartapi_mcp-0.1.1.dist-info/entry_points.txt
smartapi_mcp-0.1.1.dist-info/top_level.txt
smartapi_mcp-0.1.1.dist-info/RECORD
