Metadata-Version: 2.4
Name: smartapi-mcp
Version: 0.1.1
Summary: Create MCP servers for one or multiple APIs registered in SmartAPI registry
Author-email: BioThings Team <help@biothings.io>
Maintainer-email: BioThings Team <help@biothings.io>
License: Apache-2.0
Project-URL: Homepage, https://github.com/biothings/smartapi-mcp
Project-URL: Repository, https://github.com/biothings/smartapi-mcp
Project-URL: Issues, https://github.com/biothings/smartapi-mcp/issues
Project-URL: Documentation, https://github.com/biothings/smartapi-mcp#readme
Keywords: mcp,smartapi,api,server,bioinformatics
Classifier: Development Status :: 3 - Alpha
Classifier: Intended Audience :: Developers
Classifier: License :: OSI Approved :: Apache Software License
Classifier: Operating System :: OS Independent
Classifier: Programming Language :: Python :: 3
Classifier: Programming Language :: Python :: 3.10
Classifier: Programming Language :: Python :: 3.11
Classifier: Programming Language :: Python :: 3.12
Classifier: Programming Language :: Python :: 3.13
Classifier: Topic :: Software Development :: Libraries :: Python Modules
Classifier: Topic :: Internet :: WWW/HTTP :: HTTP Servers
Classifier: Topic :: Scientific/Engineering :: Bio-Informatics
Requires-Python: >=3.10
License-File: LICENSE
Requires-Dist: awslabs_openapi_mcp_server>=0.2.4
Provides-Extra: dev
Requires-Dist: pytest>=7.0.0; extra == "dev"
Requires-Dist: pytest-asyncio>=0.21.0; extra == "dev"
Requires-Dist: pytest-cov>=4.0.0; extra == "dev"
Requires-Dist: ruff>=0.1.0; extra == "dev"
Requires-Dist: build>=0.8.0; extra == "dev"
Requires-Dist: twine>=4.0.0; extra == "dev"
Provides-Extra: test
Requires-Dist: pytest>=7.0.0; extra == "test"
Requires-Dist: pytest-asyncio>=0.21.0; extra == "test"
Requires-Dist: pytest-cov>=4.0.0; extra == "test"
Provides-Extra: docs
Requires-Dist: sphinx>=5.0.0; extra == "docs"
Requires-Dist: sphinx-rtd-theme>=1.0.0; extra == "docs"
Dynamic: license-file
